LICENSE.txt
MANIFEST.in
README.md
setup.cfg
setup.py
OnloadTable/OnloadTable.pyd
OnloadTable/__init__.py
OnloadTable.egg-info/PKG-INFO
OnloadTable.egg-info/SOURCES.txt
OnloadTable.egg-info/dependency_links.txt
OnloadTable.egg-info/top_level.txt
OnloadTable/Function/__init__.py
OnloadTable/Function/mysqlexcel.pyd
OnloadTable/Function/optionDb.pyd
OnloadTable/Function/settings.py
OnloadTable/Function/Function/__init__.py
OnloadTable/Function/Ui/ExcelUi.pyd
OnloadTable/Function/Ui/MaskWin.pyd
OnloadTable/Function/Ui/__init__.py
OnloadTable/Ui/__init__.py
OnloadTable/Ui/onloadUi.pyd